llama_stack_client/__init__.py
llama_stack_client/_base_client.py
llama_stack_client/_client.py
llama_stack_client/_compat.py
llama_stack_client/_constants.py
llama_stack_client/_exceptions.py
llama_stack_client/_files.py
llama_stack_client/_models.py
llama_stack_client/_qs.py
llama_stack_client/_resource.py
llama_stack_client/_response.py
llama_stack_client/_streaming.py
llama_stack_client/_types.py
llama_stack_client/_version.py
llama_stack_client/_wrappers.py
llama_stack_client/pagination.py
llama_stack_client/py.typed
llama_stack_client/_utils/__init__.py
llama_stack_client/_utils/_compat.py
llama_stack_client/_utils/_datetime_parse.py
llama_stack_client/_utils/_logs.py
llama_stack_client/_utils/_proxy.py
llama_stack_client/_utils/_reflection.py
llama_stack_client/_utils/_resources_proxy.py
llama_stack_client/_utils/_streams.py
llama_stack_client/_utils/_sync.py
llama_stack_client/_utils/_transform.py
llama_stack_client/_utils/_typing.py
llama_stack_client/_utils/_utils.py
llama_stack_client/lib/.keep
llama_stack_client/lib/__init__.py
llama_stack_client/lib/stream_printer.py
llama_stack_client/lib/agents/__init__.py
llama_stack_client/lib/agents/agent.py
llama_stack_client/lib/agents/client_tool.py
llama_stack_client/lib/agents/event_logger.py
llama_stack_client/lib/agents/event_synthesizer.py
llama_stack_client/lib/agents/tool_parser.py
llama_stack_client/lib/agents/turn_events.py
llama_stack_client/lib/agents/types.py
llama_stack_client/lib/agents/react/__init__.py
llama_stack_client/lib/agents/react/agent.py
llama_stack_client/lib/agents/react/prompts.py
llama_stack_client/lib/agents/react/tool_parser.py
llama_stack_client/lib/cli/__init__.py
llama_stack_client/lib/cli/configure.py
llama_stack_client/lib/cli/constants.py
llama_stack_client/lib/cli/llama_stack_client.py
llama_stack_client/lib/cli/common/__init__.py
llama_stack_client/lib/cli/common/utils.py
llama_stack_client/lib/cli/datasets/__init__.py
llama_stack_client/lib/cli/datasets/datasets.py
llama_stack_client-0.4.4.dist-info/METADATA
llama_stack_client-0.4.4.dist-info/WHEEL
llama_stack_client-0.4.4.dist-info/entry_points.txt
llama_stack_client-0.4.4.dist-info/licenses/LICENSE
llama_stack_client-0.4.4.dist-info/RECORD
