Metadata-Version: 2.3
Name: llama_stack_client
Version: 0.4.4
Summary: The official Python library for the llama-stack-client API
Project-URL: Homepage, https://github.com/llamastack/llama-stack-client-python
Project-URL: Repository, https://github.com/llamastack/llama-stack-client-python
Author-email: Meta Llama <llama-oss@meta.com>
License: MIT
Classifier: Intended Audience :: Developers
Classifier: License :: OSI Approved :: MIT License
Classifier: Operating System :: MacOS
Classifier: Operating System :: Microsoft :: Windows
Classifier: Operating System :: OS Independent
Classifier: Operating System :: POSIX
Classifier: Operating System :: POSIX :: Linux
Classifier: Programming Language :: Python :: 3.12
Classifier: Programming Language :: Python :: 3.14
Classifier: Topic :: Software Development :: Libraries :: Python Modules
Classifier: Typing :: Typed
Requires-Python: >=3.12
Requires-Dist: anyio<5,>=3.5.0
Requires-Dist: click
Requires-Dist: distro<2,>=1.7.0
Requires-Dist: fire
Requires-Dist: httpx<1,>=0.23.0
Requires-Dist: pandas
Requires-Dist: prompt-toolkit
Requires-Dist: pyaml
Requires-Dist: pydantic<3,>=1.9.0
Requires-Dist: requests
Requires-Dist: rich
Requires-Dist: sniffio
Requires-Dist: termcolor
Requires-Dist: tqdm
Requires-Dist: typing-extensions<5,>=4.7
Provides-Extra: aiohttp
Requires-Dist: aiohttp; extra == 'aiohttp'
Requires-Dist: httpx-aiohttp>=0.1.9; extra == 'aiohttp'
